notebookc/__init__.py
notebookc/notebookc.py
joe_first-0.0.2.dist-info/LICENSE
joe_first-0.0.2.dist-info/METADATA
joe_first-0.0.2.dist-info/WHEEL
joe_first-0.0.2.dist-info/top_level.txt
joe_first-0.0.2.dist-info/RECORD
