Metadata-Version: 2.1
Name: joe-first
Version: 0.0.2
Summary: A package to convert your Jupyter Notebook
Home-page: https://github.com/JunHuaYi/first
Author: Joe Yi
Author-email: helloahua@163.com
License: UNKNOWN
Platform: UNKNOWN
Classifier: Programming Language :: Python :: 3.7
Classifier: License :: OSI Approved :: GNU General Public License v3 (GPLv3)
Requires-Dist: ipython (>=6)
Requires-Dist: nbformat (>=4)
Requires-Dist: nbconvert (>=5)
Requires-Dist: requests (>=2)
